dguard/__init__.py
dguard/asr/__init__.py
dguard/asr/infer.py
dguard/asr/aliasr/__init__.py
dguard/asr/aliasr/register.py
dguard/asr/aliasr/auto/__init__.py
dguard/asr/aliasr/auto/auto_frontend.py
dguard/asr/aliasr/auto/auto_model.py
dguard/asr/aliasr/auto/auto_tokenizer.py
dguard/asr/aliasr/bin/__init__.py
dguard/asr/aliasr/bin/compute_audio_cmvn.py
dguard/asr/aliasr/bin/export.py
dguard/asr/aliasr/bin/inference.py
dguard/asr/aliasr/bin/tokenize_text.py
dguard/asr/aliasr/bin/train.py
dguard/asr/aliasr/bin/train_ds.py
dguard/asr/aliasr/datasets/__init__.py
dguard/asr/aliasr/datasets/dataloader_entry.py
dguard/asr/aliasr/datasets/audio_datasets/__init__.py
dguard/asr/aliasr/datasets/audio_datasets/datasets.py
dguard/asr/aliasr/datasets/audio_datasets/espnet_samplers.py
dguard/asr/aliasr/datasets/audio_datasets/index_ds.py
dguard/asr/aliasr/datasets/audio_datasets/jsonl2scp.py
dguard/asr/aliasr/datasets/audio_datasets/preprocessor.py
dguard/asr/aliasr/datasets/audio_datasets/samplers.py
dguard/asr/aliasr/datasets/audio_datasets/scp2jsonl.py
dguard/asr/aliasr/datasets/audio_datasets/scp2len.py
dguard/asr/aliasr/datasets/audio_datasets/sensevoice2jsonl.py
dguard/asr/aliasr/datasets/audio_datasets/update_jsonl.py
dguard/asr/aliasr/datasets/kws_datasets/__init__.py
dguard/asr/aliasr/datasets/kws_datasets/datasets.py
dguard/asr/aliasr/datasets/llm_datasets/__init__.py
dguard/asr/aliasr/datasets/llm_datasets/datasets.py
dguard/asr/aliasr/datasets/llm_datasets/preprocessor.py
dguard/asr/aliasr/datasets/llm_datasets_qwenaudio/__init__.py
dguard/asr/aliasr/datasets/llm_datasets_qwenaudio/datasets.py
dguard/asr/aliasr/datasets/llm_datasets_vicuna/__init__.py
dguard/asr/aliasr/datasets/llm_datasets_vicuna/datasets.py
dguard/asr/aliasr/datasets/openai_datasets/__init__.py
dguard/asr/aliasr/datasets/openai_datasets/datasets.py
dguard/asr/aliasr/datasets/openai_datasets/index_ds.py
dguard/asr/aliasr/datasets/sense_voice_datasets/__init__.py
dguard_cann-1.1.8.dist-info/METADATA
dguard_cann-1.1.8.dist-info/WHEEL
dguard_cann-1.1.8.dist-info/entry_points.txt
dguard_cann-1.1.8.dist-info/top_level.txt
dguard_cann-1.1.8.dist-info/RECORD
